delayed_image/__init__.py
delayed_image/channel_spec.py
delayed_image/channel_spec.pyi
delayed_image/delayed_base.py
delayed_image/delayed_base.pyi
delayed_image/delayed_leafs.py
delayed_image/delayed_leafs.pyi
delayed_image/delayed_nodes.py
delayed_image/delayed_nodes.pyi
delayed_image/demo.py
delayed_image/demo.pyi
delayed_image/helpers.py
delayed_image/helpers.pyi
delayed_image/lazy_loaders.py
delayed_image/lazy_loaders.pyi
delayed_image/py.typed
delayed_image/sensorchan_spec.py
delayed_image/sensorchan_spec.pyi
delayed_image/util/__init__.py
delayed_image/util/util_network_text.py
delayed_image/util/util_network_text.pyi
delayed_image-0.4.6.dist-info/licenses/LICENSE
delayed_image-0.4.6.dist-info/METADATA
delayed_image-0.4.6.dist-info/WHEEL
delayed_image-0.4.6.dist-info/top_level.txt
delayed_image-0.4.6.dist-info/RECORD
